Metadata-Version: 2.4
Name: gmsh_api
Version: 4.13.1
Summary: gmsh - API for a great Finite Element Mesher
Home-page: https://github.com/lepy/gmsh_api
Author: Lepy
Author-email: lepy@tuta.io
License: GPL
Keywords: fem mesh
Classifier: Development Status :: 3 - Alpha
Classifier: Topic :: Utilities
License-File: LICENSE
Requires-Dist: numpy
Requires-Dist: pandas
Dynamic: author
Dynamic: author-email
Dynamic: classifier
Dynamic: description
Dynamic: description-content-type
Dynamic: home-page
Dynamic: keywords
Dynamic: license
Dynamic: license-file
Dynamic: requires-dist
Dynamic: summary
